as_client/__init__.py
as_client/__main__.py
as_client/client.py
as_client/exceptions.py
as_client/model.py
as_client/util.py
as_client/version.py
eratos_as_client-2.23.0.dist-info/METADATA
eratos_as_client-2.23.0.dist-info/WHEEL
eratos_as_client-2.23.0.dist-info/licenses/LICENSE
eratos_as_client-2.23.0.dist-info/RECORD
