Metadata-Version: 2.4
Name: eratos-as-client
Version: 2.23.0
Summary: Analysis Services Client
Project-URL: Homepage, https://bitbucket.csiro.au/projects/SC/repos/as-client-python/browse
Author-email: Mac Coombe <mac.coombe@csiro.au>
Maintainer-email: Eratos <support@eratos.com>
License-File: LICENSE
Keywords: Analysis-Services
Classifier: Development Status :: 3 - Alpha
Classifier: Intended Audience :: Developers
Classifier: Natural Language :: English
Classifier: Operating System :: POSIX
Classifier: Programming Language :: Python :: 3
Classifier: Programming Language :: Python :: 3.7
Classifier: Programming Language :: Python :: 3.8
Classifier: Programming Language :: Python :: 3.9
Classifier: Programming Language :: Python :: 3.10
Classifier: Programming Language :: Python :: 3.11
Classifier: Programming Language :: Python :: 3.12
Classifier: Topic :: Scientific/Engineering :: Information Analysis
Requires-Python: >=3.7
Requires-Dist: requests>=2.11.1
Provides-Extra: test
Requires-Dist: responses<1.0.0,>=0.13.2; extra == 'test'
